alright/__init__.py
alright-2.6.dist-info/LICENSE
alright-2.6.dist-info/METADATA
alright-2.6.dist-info/WHEEL
alright-2.6.dist-info/top_level.txt
alright-2.6.dist-info/RECORD
