Metadata-Version: 2.1
Name: alright
Version: 2.6
Summary: Python wrapper for WhatsApp web based on selenium
Home-page: https://github.com/Kalebu/alright
Author: Jordan Kalebu
Author-email: isaackeinstein@gmail.com
License: MIT
Download-URL: https://github.com/Kalebu/alright/archive/refs/tags/v1.7.tar.gz
Keywords: alright,python-whatsapp,PyWhatsApp,pywhatsapp,python-whatsapp-wrapper
Platform: UNKNOWN
Classifier: Development Status :: 3 - Alpha
Classifier: Intended Audience :: Developers
Classifier: Topic :: Software Development :: Build Tools
Classifier: License :: OSI Approved :: MIT License
Classifier: Programming Language :: Python :: 3.6
Classifier: Programming Language :: Python :: 3.7
Classifier: Programming Language :: Python :: 3.8
Classifier: Programming Language :: Python :: 3.9
Requires-Python: >=3.6
Requires-Dist: platformdirs
Requires-Dist: selenium
Requires-Dist: webdriver-manager
